portia/__init__.py
portia/cli.py
portia/exceptions.py
portia/portia.py
portia/protocol.py
portia/utils.py
portia/web.py
portia-1.1.0.dist-info/DESCRIPTION.rst
portia-1.1.0.dist-info/METADATA
portia-1.1.0.dist-info/RECORD
portia-1.1.0.dist-info/WHEEL
portia-1.1.0.dist-info/entry_points.txt
portia-1.1.0.dist-info/metadata.json
portia-1.1.0.dist-info/top_level.txt
