Metadata-Version: 2.0
Name: portia
Version: 1.1.0
Summary: Portia
Home-page: https://github.com/praekelt/portia
Author: Praekelt Foundation
Author-email: dev@praekeltfoundation.org
License: BSD
Keywords: portia
Platform: UNKNOWN
Classifier: Intended Audience :: Developers
Classifier: Natural Language :: English
Classifier: Programming Language :: Python :: 2.7
Requires-Dist: click (==5.1)
Requires-Dist: hiredis (==0.2.0)
Requires-Dist: klein (==15.1.0)
Requires-Dist: phonenumbers (==8.6.0)
Requires-Dist: python-dateutil (==1.5)
Requires-Dist: txredisapi (==1.3)
